AUTHORS
MANIFEST.in
NEWS
README.rst
setup.py
pyadl/__init__.py
pyadl/adl_api.py
pyadl/adl_defines.py
pyadl/adl_structures.py
pyadl/pyadl.py
pyadl.egg-info/PKG-INFO
pyadl.egg-info/SOURCES.txt
pyadl.egg-info/dependency_links.txt
pyadl.egg-info/top_level.txt