Metadata-Version: 1.1
Name: pyadl
Version: 0.1
Summary: A simple Python Wrapper for the AMD/ATI ADL lib.
Home-page: https://github.com/nicolargo/pyadl
Author: Gergo Szabo (aka) hunasdf
Author-email: szager88@hmail.com
License: MIT
Keywords: amd ati driver wrapper monitoring gpu
Platform: UNKNOWN
Classifier: Development Status :: 4 - Beta
Classifier: License :: OSI Approved :: MIT License
Classifier: Programming Language :: Python :: 2
Classifier: Programming Language :: Python :: 3
Classifier: Topic :: System :: Hardware :: Hardware Drivers
Classifier: Topic :: System :: Monitoring
